MEM_FIFO_SA.v
module location_memory(in,out,clk);
input[5:0] in;
input clk;
output reg[7:0] out;
reg[7:0] mem[0:63];
always @(posedge clk) begin
    if(in==8'hFF)out<={8{1'b1}};
    else begin
      out<=mem[in];
    end
end
endmodule
module location_memory_counter(out,clr,clk,com);
input clk,clr;
output reg com;
output[5:0] out;
reg[5:0] counter;
assign out=counter;
always @(posedge clk) begin
    if(clr)begin counter<=6'b000000;com<=1'b0; end
    else if(counter==6'b101100)begin counter<=6'b000000;com<=1'b1; end
    else begin counter<=counter+1;com<=1'b0; end
end
endmodule
module location_to_index_A(base_address,location_memory_out,memory_in);
parameter  N=32;
parameter M=256;
parameter width = 8;
parameter row = 5;
input[width-1:0] base_address;
input[width-1:0] location_memory_out;
output reg[width-1:0] memory_in;
always @(*) begin
    if(location_memory_out==8'b11111111)memory_in<=8'b11111111;
    else begin
      memory_in<={4'b0000,location_memory_out[7:4]}*row+{4'b0000,location_memory_out[3:0]};
    end
end
endmodule
module location_to_index_B(base_address,location_memory_out,memory_in);
parameter  N=32;
parameter M=256;
parameter width = 8;
parameter row = 5;
input[width-1:0] base_address;
input[width-1:0] location_memory_out;
output reg[width-1:0] memory_in;
always @(*) begin
    if(location_memory_out==8'b11111111)memory_in<=8'b11111111;
    else begin
      memory_in<={4'b0000,location_memory_out[3:0]}*row+{4'b0000,location_memory_out[7:4]};
    end
end
endmodule
module memory(in,out,clk);
parameter width =8;
parameter N = 32;
input clk;
input[width-1:0] in;
output reg[N-1:0] out;
reg[N-1:0] mem[0:256];
always @(posedge clk) begin
    if(in==8'b11111111)out<=8'b00000000;
    else out<=mem[in];
end
endmodule
module de_mux(sel,in,out0,out1,out2,out3,out4);
parameter N =32;
input[2:0] sel;
input[N-1:0] in;
output reg[N-1:0] out0,out1,out2,out3,out4;
always @(*) begin
    case(sel)
    3'b000:out0<=in;
    3'b001:out1<=in;
    3'b010:out2<=in;
    3'b011:out3<=in;
    3'b100:out4<=in;
    default:begin out0<={8{1'b0}};out1<={8{1'b0}};out2<={8{1'b0}};out3<={8{1'b0}};out4<={8{1'b0}}; end
    endcase
end
endmodule
module de_mux_counter(out,clr,clk);
input clk,clr;
output[2:0] out;
reg[2:0] counter;
assign out=counter;
always @(posedge clk) begin
    if(clr)counter<=6'b000;
    else if(counter==6'b100)counter<=6'b000;
    else counter<=counter+1;
end
endmodule
module computational_block_A(LM_clr,de_mux_clr,com,dmux_sel_out,base_address,clk,out0,out1,out2,out3,out4);
input LM_clr,de_mux_clr,clk;
output com;
input[7:0] base_address;
output[31:0] out0,out1,out2,out3,out4;
output[2:0] dmux_sel_out;
wire[5:0] LM_counter_out;
wire[7:0] LM_data;
wire[7:0] mem_address;
wire[31:0] mem_data;
wire[2:0] dmux_sel;
assign dmux_sel_out=dmux_sel;
location_memory_counter LMC(LM_counter_out,LM_clr,clk,com);
location_memory LM(LM_counter_out,LM_data,clk);
location_to_index_A LtoI(base_address,LM_data,mem_address);
memory MEM(mem_address,mem_data,clk);
de_mux_counter DMC(dmux_sel,de_mux_clr,clk);
de_mux DM(dmux_sel,mem_data,out0,out1,out2,out3,out4);
endmodule
module computational_block_B(LM_clr,de_mux_clr,com,dmux_sel_out,base_address,clk,out0,out1,out2,out3,out4);
input LM_clr,de_mux_clr,clk;
output com;
input[7:0] base_address;
output[31:0] out0,out1,out2,out3,out4;
output[2:0] dmux_sel_out;
wire[5:0] LM_counter_out;
wire[7:0] LM_data;
wire[7:0] mem_address;
wire[31:0] mem_data;
wire[2:0] dmux_sel;
assign dmux_sel_out=dmux_sel;
location_memory_counter LMC(LM_counter_out,LM_clr,clk,com);
location_memory LM(LM_counter_out,LM_data,clk);
location_to_index_B LtoI(base_address,LM_data,mem_address);
memory MEM(mem_address,mem_data,clk);
de_mux_counter DMC(dmux_sel,de_mux_clr,clk);
de_mux DM(dmux_sel,mem_data,out0,out1,out2,out3,out4);
endmodule
module controller(init,com,base_address_in,LM_clr,de_mux_clr,base_address,clk);
input init,com,clk;
input[7:0] base_address_in;
output reg LM_clr,de_mux_clr;
output reg[7:0] base_address;
reg[2:0] state;
parameter  S0=3'b000,S1=3'b001,S2=3'b010,S3=3'b011,S4=3'b100;
always @(posedge clk) begin
    case(state)
    S0:state<=init?S1:S0;
    S1:state<=S2;
    S2:state<=S3;
    S3:state<=com?S4:S3;
    S4:state<=S0;
    endcase
end
always @(state) begin
    case(state)
    S0:begin LM_clr<=1'b1;de_mux_clr<=1'b1;base_address<=base_address_in; end
    S1:begin LM_clr<=1'b0;de_mux_clr<=1'b1; end
    S2:begin LM_clr<=1'b0;de_mux_clr<=1'b1; end
    S3:begin LM_clr<=1'b0;de_mux_clr<=1'b0; end
    S4:begin LM_clr<=1'b0;de_mux_clr<=1'b0; end
    endcase
end
endmodule
module input_of_FIFO_A(init,com,de_mux_clr_out,dmux_sel_out,base_address,clk,out0,out1,out2,out3,out4);
input init,clk;
output com;
input[7:0] base_address;
output[31:0] out0,out1,out2,out3,out4;
output de_mux_clr_out;
output[2:0] dmux_sel_out;
wire LM_clr,de_mux_clr;
wire[7:0] base_address_ctrl;
wire complete;
assign com=complete;
assign de_mux_clr_out=de_mux_clr;
computational_block_A CB(LM_clr,de_mux_clr,complete,dmux_sel_out,base_address_ctrl,clk,out0,out1,out2,out3,out4);
controller CN(init,complete,base_address,LM_clr,de_mux_clr,base_address_ctrl,clk);
endmodule
module input_of_FIFO_B(init,com,de_mux_clr_out,dmux_sel_out,base_address,clk,out0,out1,out2,out3,out4);
input init,clk;
output com;
input[7:0] base_address;
output[31:0] out0,out1,out2,out3,out4;
output de_mux_clr_out;
output[2:0] dmux_sel_out;
wire LM_clr,de_mux_clr;
wire[7:0] base_address_ctrl;
wire complete;
assign com=complete;
assign de_mux_clr_out=de_mux_clr;
computational_block_B CB(LM_clr,de_mux_clr,complete,dmux_sel_out,base_address_ctrl,clk,out0,out1,out2,out3,out4);
controller CN(init,complete,base_address,LM_clr,de_mux_clr,base_address_ctrl,clk);
endmodule
module FIFO(clk,rst,buf_in,buf_out,wr_en,rd_en,buf_empty,buf_full);
parameter N=32;
input rst,clk,wr_en,rd_en;
input[N-1:0] buf_in;
output reg[N-1:0] buf_out;
output reg buf_empty,buf_full;
reg[6:0] fifo_counter;
reg[5:0] rd_ptr,wr_ptr;
reg[N-1:0] buf_mem[63:0];
always @(fifo_counter) begin
    buf_empty<=(fifo_counter==0);
    buf_full<=(fifo_counter==64);
end
always @(posedge clk or posedge rst)begin
    if(rst)fifo_counter<=0;
    else if((!buf_full && wr_en) && (!buf_empty && rd_en))fifo_counter<=fifo_counter;
    else if(!buf_full && wr_en) fifo_counter<=fifo_counter+1;
    else if(!buf_empty && rd_en)fifo_counter<=fifo_counter-1;
    else fifo_counter<=fifo_counter;
end
always @(posedge clk or posedge rst)begin
    if(rst)buf_out<=0;
    else begin
        if(rd_en && !buf_empty)
        buf_out<=buf_mem[rd_ptr];
        else
        buf_out<=buf_out;
    end
end
always @(posedge clk)begin
    if(wr_en && !buf_full)buf_mem[wr_ptr]<=buf_in;
    else buf_mem[wr_ptr]<=buf_mem[wr_ptr];
end
always @(posedge clk or posedge rst)begin
    if(rst)begin
        wr_ptr<=0;
        rd_ptr<=0;
    end
    else begin
        if(!buf_full && wr_en)wr_ptr<=wr_ptr+1;
        else wr_ptr<=wr_ptr;
        if(!buf_empty && rd_en)rd_ptr<=rd_ptr+1;
        else rd_ptr<=rd_ptr;
end
end
endmodule
module signal_to_FIFO(demux_clr,demux_sel,write_en);
input demux_clr;
input[2:0] demux_sel;
output reg[4:0] write_en;
always @(*) begin
    case(demux_sel)
    3'b000:write_en<=demux_clr?5'b00000:5'b00001;
    3'b001:write_en<=demux_clr?5'b00000:5'b00010;
    3'b010:write_en<=demux_clr?5'b00000:5'b00100;
    3'b011:write_en<=demux_clr?5'b00000:5'b01000;
    3'b100:write_en<=demux_clr?5'b00000:5'b10000;
    default:write_en<=5'b00000;
    endcase
end
endmodule
module MEM_FIFO_A(init,com,clk,rst,rd_en,base_address,out0,out1,out2,out3,out4);
input init,clk,rst;
output com;
output[31:0] out0,out1,out2,out3,out4;
input[7:0] base_address;
input[4:0] rd_en;
wire[31:0] in0,in1,in2,in3,in4;
wire[4:0] wr_en,buf_empty,buf_full;
wire[2:0] dmux_sel_out;
wire en;
assign en=&buf_full;
input_of_FIFO_A IOF(init & ~en,com,de_mux_clr_out,dmux_sel_out,base_address,clk,in0,in1,in2,in3,in4);
FIFO F0(clk,rst,in0,out0,wr_en[0],rd_en[0],buf_empty[0],buf_full[0]);
FIFO F1(clk,rst,in1,out1,wr_en[1],rd_en[1],buf_empty[1],buf_full[1]);
FIFO F2(clk,rst,in2,out2,wr_en[2],rd_en[2],buf_empty[2],buf_full[2]);
FIFO F3(clk,rst,in3,out3,wr_en[3],rd_en[3],buf_empty[3],buf_full[3]);
FIFO F4(clk,rst,in4,out4,wr_en[4],rd_en[4],buf_empty[4],buf_full[4]);
signal_to_FIFO STF(de_mux_clr_out,dmux_sel_out,wr_en);
endmodule
module MEM_FIFO_B(init,com,clk,rst,rd_en,base_address,out0,out1,out2,out3,out4);
input init,clk,rst;
output com;
output[31:0] out0,out1,out2,out3,out4;
input[7:0] base_address;
input[4:0] rd_en;
wire[31:0] in0,in1,in2,in3,in4;
wire[4:0] wr_en,buf_empty,buf_full;
wire[2:0] dmux_sel_out;
wire en;
assign en=&buf_full;
input_of_FIFO_B IOF(init & ~en,com,de_mux_clr_out,dmux_sel_out,base_address,clk,in0,in1,in2,in3,in4);
FIFO F0(clk,rst,in0,out0,wr_en[0],rd_en[0],buf_empty[0],buf_full[0]);
FIFO F1(clk,rst,in1,out1,wr_en[1],rd_en[1],buf_empty[1],buf_full[1]);
FIFO F2(clk,rst,in2,out2,wr_en[2],rd_en[2],buf_empty[2],buf_full[2]);
FIFO F3(clk,rst,in3,out3,wr_en[3],rd_en[3],buf_empty[3],buf_full[3]);
FIFO F4(clk,rst,in4,out4,wr_en[4],rd_en[4],buf_empty[4],buf_full[4]);
signal_to_FIFO STF(de_mux_clr_out,dmux_sel_out,wr_en);
endmodule
module counter(out,clk,clr);
input clk,clr;
output reg[3:0] out;
always @(posedge clk) begin
    if(clr)out<=4'b0000;
    else out<=out+1;
end
endmodule
module Processing_Element(A,B,Aout,Bout,clk,clr,read,write);
parameter N=32;
input[N-1:0] A,B;
output reg[N-1:0] Aout,Bout;
reg[N-1:0] Acc;
input clk,clr,read,write;
always @(posedge clk)begin
    if(clr & ~read & ~write)begin
        Acc<=0;
        Aout<=0;
        Bout<=0;
    end
    // else if(~clr & read & ~write)begin
    //     Acc<=B;
    // end
    // else if(~clr & write & ~read)begin
    //     Bout<=Acc;
    // end
    // else if(clr & write & ~read)begin
    //     Bout<=Acc;
    //     Acc<=0;
    // end
    // else if(~clr & write & read)begin
    //     Bout<=Acc;
    //     Acc<=B;
    // end
    else if(~clr & read & ~write)begin
      Bout<=Acc;
    end
    else if(~clr & ~read & write )begin
      Bout<=B;
    end
    else begin
        Acc<=Acc+A*B;
        Aout<=A;
        Bout<=B;
    end
end
endmodule
module PE_layer(A0,B0,B1,B2,B3,B4,A0_out,B0_out,B1_out,B2_out,B3_out,B4_out,clk,clr,read,write);
parameter N=32;
parameter M=5;
input[N-1:0] A0,B0,B1,B2,B3,B4;
output[N-1:0] A0_out,B0_out,B1_out,B2_out,B3_out,B4_out;
input clk;
input[M-1:0] clr,read,write;
wire[N-1:0] A0_temp0,A0_temp1,A0_temp2,A0_temp3;
Processing_Element PE0(A0,B0,A0_temp0,B0_out,clk,clr[0],read[0],write[0]);
Processing_Element PE1(A0_temp0,B1,A0_temp1,B1_out,clk,clr[1],read[1],write[1]);
Processing_Element PE2(A0_temp1,B2,A0_temp2,B2_out,clk,clr[2],read[2],write[2]);
Processing_Element PE3(A0_temp2,B3,A0_temp3,B3_out,clk,clr[3],read[3],write[3]);
Processing_Element PE4(A0_temp3,B4,A0_out,B4_out,clk,clr[4],read[4],write[4]);
endmodule
module Systolic_Array(A0,A1,A2,A3,A4,B0,B1,B2,B3,B4,A0_out,A1_out,A2_out,A3_out,A4_out,B0_out,B1_out,B2_out,B3_out,B4_out,clk,clr,clr_C,read,write);
parameter N=32;
parameter M=25;
input[N-1:0] A0,A1,A2,A3,A4,B0,B1,B2,B3,B4;
output[N-1:0] A0_out,A1_out,A2_out,A3_out,A4_out,B0_out,B1_out,B2_out,B3_out,B4_out;
input clk,clr_C;
input[M-1:0] clr,read,write;
wire[3:0] cout;
wire[N-1:0] B0_temp0,B1_temp0,B2_temp0,B3_temp0,B4_temp0;
wire[N-1:0] B0_temp1,B1_temp1,B2_temp1,B3_temp1,B4_temp1;
wire[N-1:0] B0_temp2,B1_temp2,B2_temp2,B3_temp2,B4_temp2;
wire[N-1:0] B0_temp3,B1_temp3,B2_temp3,B3_temp3,B4_temp3;
counter C0(cout,clk,clr_C);
PE_layer PE_layer0(A0,B0,B1,B2,B3,B4,A0_out,B0_temp0,B1_temp0,B2_temp0,B3_temp0,B4_temp0,clk,clr[4:0],read[4:0],write[4:0]);
PE_layer PE_layer1(A1,B0_temp0,B1_temp0,B2_temp0,B3_temp0,B4_temp0,A1_out,B0_temp1,B1_temp1,B2_temp1,B3_temp1,B4_temp1,clk,clr[9:5],read[9:5],write[9:5]);
PE_layer PE_layer2(A2,B0_temp1,B1_temp1,B2_temp1,B3_temp1,B4_temp1,A2_out,B0_temp2,B1_temp2,B2_temp2,B3_temp2,B4_temp2,clk,clr[14:10],read[14:10],write[14:10]);
PE_layer PE_layer3(A3,B0_temp2,B1_temp2,B2_temp2,B3_temp2,B4_temp2,A3_out,B0_temp3,B1_temp3,B2_temp3,B3_temp3,B4_temp3,clk,clr[19:15],read[19:15],write[19:15]);
PE_layer PE_layer4(A4,B0_temp3,B1_temp3,B2_temp3,B3_temp3,B4_temp3,A4_out,B0_out,B1_out,B2_out,B3_out,B4_out,clk,clr[24:20],read[24:20],write[24:20]);
endmodule
// module counter(out,clk,clr);
// input clk,clr;
// output reg[3:0] out;
// always @(posedge clk) begin
//     if(clr)out<=4'b0000;
//     else out<=out+1;
// end
// endmodule
module Controller(init,complete,C,read,write,clr,clr_C,rd_en,wr_en,clk);
input init,clk;
input[3:0] C;
output reg[24:0] read,write,clr;
output reg clr_C,rd_en,wr_en,complete;
reg[2:0] state;
parameter Sinit=3'b000,S1=3'b001,S2=3'b010,S3=3'b011,S4=3'b100,S5=3'b101;
always @(posedge clk) begin
    case (state)
        Sinit:state<=init?S1:Sinit;
        S1:state<=(C==4'b1010)?S2:S1;
        S2:state<=(C==4'b1101)?S3:S2;
        S3:state<=S4;
        S4:state<=(C==4'b0011)?S5:S4;
        S5:state<=Sinit;
    endcase
end
always @(state) begin
    case(state)
    Sinit:begin read<=25'b0;write<=25'b0;clr={25{1'b1}};clr_C<=1'b1;rd_en<=1'b0;wr_en<=1'b0;complete<=1'b0; end
    S1:begin read<=25'b0;write<=25'b0;clr<=25'b0;clr_C<=1'b0;rd_en<=1'b1; end
    S2:begin read<=25'b0;write<=25'b0;clr<=25'b0;clr_C<=1'b0;rd_en<=1'b0; end
    S3:begin read<={25{1'b1}};write<=25'b0;clr<=25'b0;clr_C<=1'b1;rd_en<=1'b0; end
    S4:begin read<=25'b0;write<={25{1'b1}};clr<=25'b0;clr_C<=1'b0;wr_en<=1'b1; end
    S5:begin read<=25'b0;write<={25{1'b0}};clr<={25{1'b1}};clr_C<=1'b0;wr_en<=1'b1;complete<=1'b1; end
    endcase
end
endmodule
module Systolic_Array_Controller(init,complete,read,write,clr,clr_C,rd_en,wr_en,clk);
input init,clk;
output[24:0] read,write,clr;
output clr_C;
output rd_en,wr_en,complete;
//wire clr_C;
wire[3:0] C;
Controller C1(init,complete,C,read,write,clr,clr_C,rd_en,wr_en,clk);
counter co(C,clk,clr_C);
endmodule
module Systolic_Array_with_Controller(init,complete,clk,rd_en,wr_en,A0,A1,A2,A3,A4,B0,B1,B2,B3,B4,A0_out,A1_out,A2_out,A3_out,A4_out,B0_out,B1_out,B2_out,B3_out,B4_out);
parameter N=32;
parameter M=25;
input[N-1:0] A0,A1,A2,A3,A4,B0,B1,B2,B3,B4;
output[N-1:0] A0_out,A1_out,A2_out,A3_out,A4_out,B0_out,B1_out,B2_out,B3_out,B4_out;
input init,clk;
output rd_en,wr_en,complete;
wire[24:0] read,write,clr;
wire clr_C;
Systolic_Array_Controller SAC(init,complete,read,write,clr,clr_C,rd_en,wr_en,clk);
Systolic_Array SA(A0,A1,A2,A3,A4,B0,B1,B2,B3,B4,A0_out,A1_out,A2_out,A3_out,A4_out,B0_out,B1_out,B2_out,B3_out,B4_out,clk,clr,clr_C,read,write);
endmodule
// module MEM_FIFO_SA_Controller(clk,rst,com_A,com_B,rd_en_A,rd_en_B);
// input clk,rst,com_A,com_B;
// output reg[4:0] rd_en_A,rd_en_B;
// always @(posedge clk) begin
// end
// endmodule
module counter_A(clk,rst,inc,dec,com);
input clk,rst,inc,dec;
output com;
reg[5:0] count;
always @(posedge clk) begin
    if(rst)count<=5'b00000;
    else if(inc)count<=count+1;
    else if(dec)count<=count-1;
    else count<=count;
end
assign com=rst?1'b0:(|count);
endmodule
module MEM_FIFO_SA(init,clk,rst,base_address_A,base_address_B,A0_out,A1_out,A2_out,A3_out,A4_out,B0_out,B1_out,B2_out,B3_out,B4_out);
parameter N = 32;
input init,clk,rst;
input[7:0] base_address_A,base_address_B;
output[N-1:0] A0_out,A1_out,A2_out,A3_out,A4_out,B0_out,B1_out,B2_out,B3_out,B4_out;
wire[N-1:0] A0,A1,A2,A3,A4;
wire[N-1:0] B0,B1,B2,B3,B4;
wire com_A,com_B,com_SA;
wire rd_en,wr_en,init_SA;
MEM_FIFO_A MFA(init,com_A,clk,rst,{5{rd_en}},base_address_A,A0,A1,A2,A3,A4);
MEM_FIFO_B MFB(init,com_B,clk,rst,{5{rd_en}},base_address_B,B0,B1,B2,B3,B4);
counter_A CoA(clk,rst,com_A,com_SA,init_SA);
Systolic_Array_with_Controller SAC(init_SA,com_SA,clk,rd_en,wr_en,A0,A1,A2,A3,A4,B0,B1,B2,B3,B4,A0_out,A1_out,A2_out,A3_out,A4_out,B0_out,B1_out,B2_out,B3_out,B4_out);
endmodule

FIFO_test.v
module FIFO_test;
parameter N=32;
reg rst,clk,wr_en,rd_en;
reg[N-1:0] buf_in;
wire[N-1:0] buf_out;
wire buf_empty,buf_full;
integer seed;
integer i;
FIFO DUT(clk,rst,buf_in,buf_out,wr_en,rd_en,buf_empty,buf_full);
initial begin
    clk=0;
    rst=1;
    wr_en=0;
    rd_en=0;
    seed=10;
    buf_in=$urandom(seed)%100;
    $write("%d ",buf_in);
    #10 wr_en=1;
    for(i=0;i<44;i=i+1)begin
    #10 buf_in=$urandom(seed)%100;rst=0;$write("%d ",buf_in);
    end
    $write("\n");
    #10 buf_in=0;wr_en=1;rd_en=1;
    #200 for (i=0;i<64;i=i+1)begin
        $write("%d",DUT.buf_mem[i]);
    end
    $write("\n");
    #10 $finish;
end
always #5 clk=~clk;
initial begin
    $dumpfile("FIFO_test.vcd");
    $dumpvars(0,FIFO_test);
end
endmodule

FIFO_test.vcd
$date
	Wed Sep 28 11:27:44 2022
$end
$version
	Icarus Verilog
$end
$timescale
	1s
$end
$scope module FIFO_test $end
$var wire 1 ! buf_empty $end
$var wire 1 " buf_full $end
$var wire 32 # buf_out [31:0] $end
$var reg 32 $ buf_in [31:0] $end
$var reg 1 % clk $end
$var integer 32 & i [31:0] $end
$var reg 1 ' rd_en $end
$var reg 1 ( rst $end
$var integer 32 ) seed [31:0] $end
$var reg 1 * wr_en $end
$scope module DUT $end
$var wire 32 + buf_in [31:0] $end
$var wire 1 , clk $end
$var wire 1 - rd_en $end
$var wire 1 . rst $end
$var wire 1 / wr_en $end
$var reg 1 0 buf_empty $end
$var reg 1 1 buf_full $end
$var reg 32 2 buf_out [31:0] $end
$var reg 7 3 fifo_counter [6:0] $end
$var reg 6 4 rd_ptr [5:0] $end
$var reg 6 5 wr_ptr [5:0] $end
$upscope $end
$upscope $end
$enddefinitions $end
#0
$dumpvars
b0 5
b0 4
b0 3
b0 2
01
10
0/
1.
0-
0,
b0 +
0*
b10101000101000000011 )
1(
0'
bx &
0%
b0 $
b0 #
0"
1!
$end
#5
1%
1,
#10
0%
0,
b0 &
1*
1/
#15
1%
1,
#20
0%
0,
b1 &
0(
0.
b11110 $
b11110 +
b11011011101011010101101101000 )
#25
00
0!
b1 5
b1 3
1%
1,
#30
0%
0,
b10 &
b110100 $
b110100 +
b10100010010101101000101001001001 )
#35
b10 3
b10 5
1%
1,
#40
0%
0,
b11 &
b110001 $
b110001 +
b11101110100110110111000101110110 )
#45
b11 5
b11 3
1%
1,
#50
0%
0,
b100 &
b1011001 $
b1011001 +
b1101000101100101101100101111111 )
#55
b100 3
b100 5
1%
1,
#60
0%
0,
b101 &
b1001111 $
b1001111 +
b11000101110000101001110110110100 )
#65
b101 5
b101 3
1%
1,
#70
0%
0,
b110 &
b100001 $
b100001 +
b11011100100011100110110100100101 )
#75
b110 3
b110 5
1%
1,
#80
0%
0,
b111 &
b1100001 $
b1100001 +
b1000110101111010100011110100010 )
#85
b111 5
b111 3
1%
1,
#90
0%
0,
b1000 &
b10011 $
b10011 +
b10001001110101111001011010111011 )
#95
b1000 3
b1000 5
1%
1,
#100
0%
0,
b1001 &
b111010 $
b111010 +
b11101011000001100011001011000000 )
#105
b1001 5
b1001 3
1%
1,
#110
0%
0,
b1010 &
b10110111010010100110001111000001 )
#115
b1010 3
b1010 5
1%
1,
#120
0%
0,
b1011 &
b11110001011000111010111010001110 )
#125
b1011 5
b1011 3
1%
1,
#130
0%
0,
b1100 &
b10010 $
b10010 +
b1011001111011111110110110111 )
#135
b1100 3
b1100 5
1%
1,
#140
0%
0,
b1101 &
b1000000 $
b1000000 +
b100100001111010111011010001100 )
#145
b1101 5
b1101 3
1%
1,
#150
0%
0,
b1110 &
b1010001 $
b1010001 +
b10011010110010010000101000011101 )
#155
b1110 3
b1110 5
1%
1,
#160
0%
0,
b1111 &
b101001 $
b101001 +
b110010100111011001001000111010 )
#165
b1111 5
b1111 3
1%
1,
#170
0%
0,
b10000 &
b1001 $
b1001 +
b11010110101010000101001110011 )
#175
b10000 3
b10000 5
1%
1,
#180
0%
0,
b10001 &
b100101 $
b100101 +
b1011000100101000011010100011000 )
#185
b10001 5
b10001 3
1%
1,
#190
0%
0,
b10010 &
b10100 $
b10100 +
b10101010011110001011110000111001 )
#195
b10010 3
b10010 5
1%
1,
#200
0%
0,
b10011 &
b100100 $
b100100 +
b1100000011101101001111010100110 )
#205
b10011 5
b10011 3
1%
1,
#210
0%
0,
b10100 &
b1011011 $
b1011011 +
b11100011101100010111100011101111 )
#215
b10100 3
b10100 5
1%
1,
#220
0%
0,
b10101 &
b10 $
b10 +
b11010001001100001111101001100100 )
#225
b10101 5
b10101 3
1%
1,
#230
0%
0,
b10110 &
b10010 $
b10010 +
b11111011010100111001011000010101 )
#235
b10110 3
b10110 5
1%
1,
#240
0%
0,
b10111 &
b110001 $
b110001 +
b10110101000110011111111010010 )
#245
b10111 5
b10111 3
1%
1,
#250
0%
0,
b11000 &
b1010101 $
b1010101 +
b10101010110010011100010100101011 )
#255
b11000 3
b11000 5
1%
1,
#260
0%
0,
b11001 &
b110011 $
b110011 +
b11000111110000010001001001110000 )
#265
b11001 5
b11001 3
1%
1,
#270
0%
0,
b11010 &
b1000011 $
b1000011 +
b11010101111110110111001110110001 )
#275
b11010 3
b11010 5
1%
1,
#280
0%
0,
b11011 &
b1100001 $
b1100001 +
b10010010111011001010000110111110 )
#285
b11011 5
b11011 3
1%
1,
#290
0%
0,
b11100 &
b110110 $
b110110 +
b1001101011100100010101100100111 )
#295
b11100 3
b11100 5
1%
1,
#300
0%
0,
b11101 &
b11 $
b11 +
b11111011110001001000100100111100 )
#305
b11101 5
b11101 3
1%
1,
#310
0%
0,
b11110 &
b1011101 $
b1011101 +
b100000100101011111000100001101 )
#315
b11110 3
b11110 5
1%
1,
#320
0%
0,
b11111 &
b1000100 $
b1000100 +
b10100110010111001011000001101010 )
#325
b11111 5
b11111 3
1%
1,
#330
0%
0,
b100000 &
b111 $
b111 +
b10011101100110001010011011100011 )
#335
b100000 3
b100000 5
1%
1,
#340
0%
0,
b100001 &
b1010001 $
b1010001 +
b10011010100110100010101011001000 )
#345
b100001 5
b100001 3
1%
1,
#350
0%
0,
b100010 &
b1000000 $
b1000000 +
b11001100011010000110101000101001 )
#355
b100010 3
b100010 5
1%
1,
#360
0%
0,
b100011 &
b1010 $
b1010 +
b1100111001010100001011111010110 )
#365
b100011 5
b100011 3
1%
1,
#370
0%
0,
b100100 &
b111011 $
b111011 +
b11010111110000001111010001011111 )
#375
b100100 3
b100100 5
1%
1,
#380
0%
0,
b100101 &
b100 $
b100 +
b10000110010010111000001100010100 )
#385
b100101 5
b100101 3
1%
1,
#390
0%
0,
b100110 &
b100010 $
b100010 +
b11100011001100111111101100000101 )
#395
b100110 3
b100110 5
1%
1,
#400
0%
0,
b100111 &
b1011110 $
b1011110 +
b10001111011001000100010000000010 )
#405
b100111 5
b100111 3
1%
1,
#410
0%
0,
b101000 &
b101 $
b101 +
b101110110000001000111110011011 )
#415
b101000 3
b101000 5
1%
1,
#420
0%
0,
b101001 &
b1011010 $
b1011010 +
b11000111000110001101111000100000 )
#425
b101001 5
b101001 3
1%
1,
#430
0%
0,
b101010 &
b1001100 $
b1001100 +
b10010000010100010111111110100001 )
#435
b101010 3
b101010 5
1%
1,
#440
0%
0,
b101011 &
b101100 $
b101100 +
b110100010111110110000011101110 )
#445
b101011 5
b101011 3
1%
1,
#450
0%
0,
b101100 &
b10010 $
b10010 +
b101001001110101011010010010111 )
#455
b101100 3
b101100 5
1%
1,
#460
0%
0,
1'
1-
b0 $
b0 +
#465
b1 4
b101101 5
b11110 2
b11110 #
1%
1,
#470
0%
0,
#475
b110100 2
b110100 #
b10 4
b101110 5
1%
1,
#480
0%
0,
#485
b11 4
b101111 5
b110001 2
b110001 #
1%
1,
#490
0%
0,
#495
b1011001 2
b1011001 #
b100 4
b110000 5
1%
1,
#500
0%
0,
#505
b101 4
b110001 5
b1001111 2
b1001111 #
1%
1,
#510
0%
0,
#515
b100001 2
b100001 #
b110 4
b110010 5
1%
1,
#520
0%
0,
#525
b111 4
b110011 5
b1100001 2
b1100001 #
1%
1,
#530
0%
0,
#535
b10011 2
b10011 #
b1000 4
b110100 5
1%
1,
#540
0%
0,
#545
b1001 4
b110101 5
b111010 2
b111010 #
1%
1,
#550
0%
0,
#555
b1010 4
b110110 5
1%
1,
#560
0%
0,
#565
b1011 4
b110111 5
1%
1,
#570
0%
0,
#575
b10010 2
b10010 #
b1100 4
b111000 5
1%
1,
#580
0%
0,
#585
b1101 4
b111001 5
b1000000 2
b1000000 #
1%
1,
#590
0%
0,
#595
b1010001 2
b1010001 #
b1110 4
b111010 5
1%
1,
#600
0%
0,
#605
b1111 4
b111011 5
b101001 2
b101001 #
1%
1,
#610
0%
0,
#615
b1001 2
b1001 #
b10000 4
b111100 5
1%
1,
#620
0%
0,
#625
b10001 4
b111101 5
b100101 2
b100101 #
1%
1,
#630
0%
0,
#635
b10100 2
b10100 #
b10010 4
b111110 5
1%
1,
#640
0%
0,
#645
b10011 4
b111111 5
b100100 2
b100100 #
1%
1,
#650
0%
0,
#655
b1011011 2
b1011011 #
b10100 4
b0 5
1%
1,
#660
0%
0,
b1000000 &
#665
b10101 4
b1 5
b10 2
b10 #
1%
1,
