Systolic_Array_with_Controller.v
module counter(out,clk,clr);
input clk,clr;
output reg[3:0] out;
always @(posedge clk) begin
    if(clr)out<=4'b0000;
    else out<=out+1;
end
endmodule
module Processing_Element(A,B,Aout,Bout,clk,clr,read,write);
parameter N=32;
input[N-1:0] A,B;
output reg[N-1:0] Aout,Bout;
reg[N-1:0] Acc;
input clk,clr,read,write;
always @(posedge clk)begin
    if(clr & ~read & ~write)begin
        Acc<=0;
        Aout<=0;
        Bout<=0;
    end
    // else if(~clr & read & ~write)begin
    //     Acc<=B;
    // end
    // else if(~clr & write & ~read)begin
    //     Bout<=Acc;
    // end
    // else if(clr & write & ~read)begin
    //     Bout<=Acc;
    //     Acc<=0;
    // end
    // else if(~clr & write & read)begin
    //     Bout<=Acc;
    //     Acc<=B;
    // end
    else if(~clr & read & ~write)begin
      Bout<=Acc;
    end
    else if(~clr & ~read & write )begin
      Bout<=B;
    end
    else begin
        Acc<=Acc+A*B;
        Aout<=A;
        Bout<=B;
    end
end
endmodule
module PE_layer(A0,B0,B1,B2,B3,B4,A0_out,B0_out,B1_out,B2_out,B3_out,B4_out,clk,clr,read,write);
parameter N=32;
parameter M=5;
input[N-1:0] A0,B0,B1,B2,B3,B4;
output[N-1:0] A0_out,B0_out,B1_out,B2_out,B3_out,B4_out;
input clk;
input[M-1:0] clr,read,write;
wire[N-1:0] A0_temp0,A0_temp1,A0_temp2,A0_temp3;
Processing_Element PE0(A0,B0,A0_temp0,B0_out,clk,clr[0],read[0],write[0]);
Processing_Element PE1(A0_temp0,B1,A0_temp1,B1_out,clk,clr[1],read[1],write[1]);
Processing_Element PE2(A0_temp1,B2,A0_temp2,B2_out,clk,clr[2],read[2],write[2]);
Processing_Element PE3(A0_temp2,B3,A0_temp3,B3_out,clk,clr[3],read[3],write[3]);
Processing_Element PE4(A0_temp3,B4,A0_out,B4_out,clk,clr[4],read[4],write[4]);
endmodule
module Systolic_Array(A0,A1,A2,A3,A4,B0,B1,B2,B3,B4,A0_out,A1_out,A2_out,A3_out,A4_out,B0_out,B1_out,B2_out,B3_out,B4_out,clk,clr,clr_C,read,write);
parameter N=32;
parameter M=25;
input[N-1:0] A0,A1,A2,A3,A4,B0,B1,B2,B3,B4;
output[N-1:0] A0_out,A1_out,A2_out,A3_out,A4_out,B0_out,B1_out,B2_out,B3_out,B4_out;
input clk,clr_C;
input[M-1:0] clr,read,write;
wire[3:0] cout;
wire[N-1:0] B0_temp0,B1_temp0,B2_temp0,B3_temp0,B4_temp0;
wire[N-1:0] B0_temp1,B1_temp1,B2_temp1,B3_temp1,B4_temp1;
wire[N-1:0] B0_temp2,B1_temp2,B2_temp2,B3_temp2,B4_temp2;
wire[N-1:0] B0_temp3,B1_temp3,B2_temp3,B3_temp3,B4_temp3;
counter C0(cout,clk,clr_C);
PE_layer PE_layer0(A0,B0,B1,B2,B3,B4,A0_out,B0_temp0,B1_temp0,B2_temp0,B3_temp0,B4_temp0,clk,clr[4:0],read[4:0],write[4:0]);
PE_layer PE_layer1(A1,B0_temp0,B1_temp0,B2_temp0,B3_temp0,B4_temp0,A1_out,B0_temp1,B1_temp1,B2_temp1,B3_temp1,B4_temp1,clk,clr[9:5],read[9:5],write[9:5]);
PE_layer PE_layer2(A2,B0_temp1,B1_temp1,B2_temp1,B3_temp1,B4_temp1,A2_out,B0_temp2,B1_temp2,B2_temp2,B3_temp2,B4_temp2,clk,clr[14:10],read[14:10],write[14:10]);
PE_layer PE_layer3(A3,B0_temp2,B1_temp2,B2_temp2,B3_temp2,B4_temp2,A3_out,B0_temp3,B1_temp3,B2_temp3,B3_temp3,B4_temp3,clk,clr[19:15],read[19:15],write[19:15]);
PE_layer PE_layer4(A4,B0_temp3,B1_temp3,B2_temp3,B3_temp3,B4_temp3,A4_out,B0_out,B1_out,B2_out,B3_out,B4_out,clk,clr[24:20],read[24:20],write[24:20]);
endmodule
// module counter(out,clk,clr);
// input clk,clr;
// output reg[3:0] out;
// always @(posedge clk) begin
//     if(clr)out<=4'b0000;
//     else out<=out+1;
// end
// endmodule
module Controller(init,C,read,write,clr,clr_C,clk);
input init,clk;
input[3:0] C;
output reg[24:0] read,write,clr;
output reg clr_C;
reg[1:0] state;
parameter Sinit=2'b00,S1=2'b01,S2=2'b10,S3=2'b11;
always @(posedge clk) begin
    case (state)
        Sinit:state<=init?S1:Sinit;
        S1:state<=(C==4'b1101)?S2:S1;
        S2:state<=S3;
        S3:state<=(C==4'b0110)?Sinit:S3;
    endcase
end
always @(state) begin
    case(state)
    Sinit:begin read<=25'b0;write<=25'b0;clr={25{1'b1}};clr_C=1'b1; end
    S1:begin read<=25'b0;write<=25'b0;clr=25'b0;clr_C=1'b0; end
    S2:begin read<={25{1'b1}};write<=25'b0;clr=25'b0;clr_C=1'b1; end
    S3:begin read<=25'b0;write<={25{1'b1}};clr=25'b0;clr_C=1'b0; end
    endcase
end
endmodule
module Systolic_Array_Controller(init,read,write,clr,clr_C,clk);
input init,clk;
output[24:0] read,write,clr;
output clr_C;
//wire clr_C;
wire[3:0] C;
Controller C1(init,C,read,write,clr,clr_C,clk);
counter co(C,clk,clr_C);
endmodule
module Systolic_Array_with_Controller(init,clk,A0,A1,A2,A3,A4,B0,B1,B2,B3,B4,A0_out,A1_out,A2_out,A3_out,A4_out,B0_out,B1_out,B2_out,B3_out,B4_out);
parameter N=32;
parameter M=25;
input[N-1:0] A0,A1,A2,A3,A4,B0,B1,B2,B3,B4;
output[N-1:0] A0_out,A1_out,A2_out,A3_out,A4_out,B0_out,B1_out,B2_out,B3_out,B4_out;
input init,clk;
wire[24:0] read,write,clr;
wire clr_C;
Systolic_Array_Controller SAC(init,read,write,clr,clr_C,clk);
Systolic_Array SA(A0,A1,A2,A3,A4,B0,B1,B2,B3,B4,A0_out,A1_out,A2_out,A3_out,A4_out,B0_out,B1_out,B2_out,B3_out,B4_out,clk,clr,clr_C,read,write);
endmodule

PE_layer_test.v
module PE_layer_test;
parameter N=32;
parameter M=5;
reg[N-1:0] A0,B0,B1,B2,B3,B4;
wire[N-1:0] A0_out,B0_out,B1_out,B2_out,B3_out,B4_out;
reg clk;
reg[M-1:0] clr,read,write;
PE_layer DUT(A0,B0,B1,B2,B3,B4,A0_out,B0_out,B1_out,B2_out,B3_out,B4_out,clk,clr,read,write);
initial begin
    clk=0;
    clr=5'b11111;
    read=5'b00000;
    write=5'b00000;
    A0=3;B0=1;B1=2;B2=3;B3=4;B4=5;
    #10 clr=5'b00000;
    #200 $finish;
end
always #5 clk=~clk;
initial begin
    $dumpfile("PE_layer_test.vcd");
    $dumpvars(0,PE_layer_test);
end
endmodule

PE_layer_test.vcd
$date
	Fri Sep 16 11:10:00 2022
$end
$version
	Icarus Verilog
$end
$timescale
	1s
$end
$scope module PE_layer_test $end
$var wire 32 ! A0_out [31:0] $end
$var wire 32 " B0_out [31:0] $end
$var wire 32 # B1_out [31:0] $end
$var wire 32 $ B2_out [31:0] $end
$var wire 32 % B3_out [31:0] $end
$var wire 32 & B4_out [31:0] $end
$var reg 32 ' A0 [31:0] $end
$var reg 32 ( B0 [31:0] $end
$var reg 32 ) B1 [31:0] $end
$var reg 32 * B2 [31:0] $end
$var reg 32 + B3 [31:0] $end
$var reg 32 , B4 [31:0] $end
$var reg 1 - clk $end
$var reg 5 . clr [4:0] $end
$var reg 5 / read [4:0] $end
$var reg 5 0 write [4:0] $end
$scope module DUT $end
$var wire 32 1 A0 [31:0] $end
$var wire 32 2 A0_out [31:0] $end
$var wire 32 3 A0_temp0 [31:0] $end
$var wire 32 4 A0_temp1 [31:0] $end
$var wire 32 5 A0_temp2 [31:0] $end
$var wire 32 6 A0_temp3 [31:0] $end
$var wire 32 7 B0 [31:0] $end
$var wire 32 8 B0_out [31:0] $end
$var wire 32 9 B1 [31:0] $end
$var wire 32 : B1_out [31:0] $end
$var wire 32 ; B2 [31:0] $end
$var wire 32 < B2_out [31:0] $end
$var wire 32 = B3 [31:0] $end
$var wire 32 > B3_out [31:0] $end
$var wire 32 ? B4 [31:0] $end
$var wire 32 @ B4_out [31:0] $end
$var wire 1 A clk $end
$var wire 5 B clr [4:0] $end
$var wire 5 C read [4:0] $end
$var wire 5 D write [4:0] $end
$scope module PE0 $end
$var wire 32 E A [31:0] $end
$var wire 32 F B [31:0] $end
$var wire 1 A clk $end
$var wire 1 G clr $end
$var wire 1 H read $end
$var wire 1 I write $end
$var reg 32 J Acc [31:0] $end
$var reg 32 K Aout [31:0] $end
$var reg 32 L Bout [31:0] $end
$upscope $end
$scope module PE1 $end
$var wire 32 M A [31:0] $end
$var wire 32 N B [31:0] $end
$var wire 1 A clk $end
$var wire 1 O clr $end
$var wire 1 P read $end
$var wire 1 Q write $end
$var reg 32 R Acc [31:0] $end
$var reg 32 S Aout [31:0] $end
$var reg 32 T Bout [31:0] $end
$upscope $end
$scope module PE2 $end
$var wire 32 U A [31:0] $end
$var wire 32 V B [31:0] $end
$var wire 1 A clk $end
$var wire 1 W clr $end
$var wire 1 X read $end
$var wire 1 Y write $end
$var reg 32 Z Acc [31:0] $end
$var reg 32 [ Aout [31:0] $end
$var reg 32 \ Bout [31:0] $end
$upscope $end
$scope module PE3 $end
$var wire 32 ] A [31:0] $end
$var wire 32 ^ B [31:0] $end
$var wire 1 A clk $end
$var wire 1 _ clr $end
$var wire 1 ` read $end
$var wire 1 a write $end
$var reg 32 b Acc [31:0] $end
$var reg 32 c Aout [31:0] $end
$var reg 32 d Bout [31:0] $end
$upscope $end
$scope module PE4 $end
$var wire 32 e A [31:0] $end
$var wire 32 f B [31:0] $end
$var wire 1 A clk $end
$var wire 1 g clr $end
$var wire 1 h read $end
$var wire 1 i write $end
$var reg 32 j Acc [31:0] $end
$var reg 32 k Aout [31:0] $end
$var reg 32 l Bout [31:0] $end
$upscope $end
$upscope $end
$upscope $end
$enddefinitions $end
#0
$dumpvars
bx l
bx k
bx j
0i
0h
1g
b101 f
bx e
bx d
bx c
bx b
0a
0`
1_
b100 ^
bx ]
bx \
bx [
bx Z
0Y
0X
1W
b11 V
bx U
bx T
bx S
bx R
0Q
0P
1O
b10 N
bx M
bx L
bx K
bx J
0I
0H
1G
b1 F
b11 E
b0 D
b0 C
b11111 B
0A
bx @
b101 ?
bx >
b100 =
bx <
b11 ;
bx :
b10 9
bx 8
b1 7
bx 6
bx 5
bx 4
bx 3
bx 2
b11 1
b0 0
b0 /
b11111 .
0-
b101 ,
b100 +
b11 *
b10 )
b1 (
b11 '
bx &
bx %
bx $
bx #
bx "
bx !
$end
#5
b0 L
b0 "
b0 8
b0 K
b0 3
b0 M
b0 J
b0 T
b0 #
b0 :
b0 S
b0 4
b0 U
b0 R
b0 \
b0 $
b0 <
b0 [
b0 5
b0 ]
b0 Z
b0 d
b0 %
b0 >
b0 c
b0 6
b0 e
b0 b
b0 l
b0 &
b0 @
b0 k
b0 !
b0 2
b0 j
1-
1A
#10
0G
0O
0W
0_
0g
0-
0A
b0 .
b0 B
#15
b101 l
b101 &
b101 @
b100 d
b100 %
b100 >
b11 \
b11 $
b11 <
b10 T
b10 #
b10 :
b1 L
b1 "
b1 8
b11 K
b11 3
b11 M
b11 J
1-
1A
#20
0-
0A
#25
b110 J
b11 S
b11 4
b11 U
b110 R
1-
1A
#30
0-
0A
#35
b11 [
b11 5
b11 ]
b1001 Z
b1100 R
b1001 J
1-
1A
#40
0-
0A
#45
b1100 J
b10010 R
b10010 Z
b11 c
b11 6
b11 e
b1100 b
1-
1A
#50
0-
0A
#55
b11 k
b11 !
b11 2
b1111 j
b11000 b
b11011 Z
b11000 R
b1111 J
1-
1A
#60
0-
0A
#65
b10010 J
b11110 R
b100100 Z
b100100 b
b11110 j
1-
1A
#70
0-
0A
#75
b101101 j
b110000 b
b101101 Z
b100100 R
b10101 J
1-
1A
#80
0-
0A
#85
b11000 J
b101010 R
b110110 Z
b111100 b
b111100 j
1-
1A
#90
0-
0A
#95
b1001011 j
b1001000 b
b111111 Z
b110000 R
b11011 J
1-
1A
#100
0-
0A
#105
b11110 J
b110110 R
b1001000 Z
b1010100 b
b1011010 j
1-
1A
#110
0-
0A
#115
b1101001 j
b1100000 b
b1010001 Z
b111100 R
b100001 J
1-
1A
#120
0-
0A
#125
b100100 J
b1000010 R
b1011010 Z
b1101100 b
b1111000 j
1-
1A
#130
0-
0A
#135
b10000111 j
b1111000 b
b1100011 Z
b1001000 R
b100111 J
1-
1A
#140
0-
0A
#145
b101010 J
b1001110 R
b1101100 Z
b10000100 b
b10010110 j
1-
1A
#150
0-
0A
#155
b10100101 j
b10010000 b
b1110101 Z
b1010100 R
b101101 J
1-
1A
#160
0-
0A
#165
b110000 J
b1011010 R
b1111110 Z
b10011100 b
b10110100 j
1-
1A
#170
0-
0A
#175
b11000011 j
b10101000 b
b10000111 Z
b1100000 R
b110011 J
1-
1A
#180
0-
0A
#185
b110110 J
b1100110 R
b10010000 Z
b10110100 b
b11010010 j
1-
1A
#190
0-
0A
#195
b11100001 j
b11000000 b
b10011001 Z
b1101100 R
b111001 J
1-
1A
#200
0-
0A
#205
b111100 J
b1110010 R
b10100010 Z
b11001100 b
b11110000 j
1-
1A
